pyeta/__init__.py
pyETA-0.2.1.dist-info/LICENCE
pyETA-0.2.1.dist-info/METADATA
pyETA-0.2.1.dist-info/WHEEL
pyETA-0.2.1.dist-info/top_level.txt
pyETA-0.2.1.dist-info/RECORD
