Metadata-Version: 2.1
Name: pyETA
Version: 0.2.1
Summary: A python wrapper to connect to your ETA heating system
Author: Poeschl
License: Apache License
Project-URL: Homepage, https://github.com/Poeschl/pyETA
Project-URL: Bug Tracker, https://github.com/Poeschl/pyETA/issues
Keywords: ETA,meinETA,REST
Classifier: License :: OSI Approved :: Apache Software License
Classifier: Programming Language :: Python :: 3
Classifier: Programming Language :: Python :: 3.8
Classifier: Programming Language :: Python :: 3.9
Classifier: Programming Language :: Python :: 3.10
Classifier: Programming Language :: Python :: 3.11
Requires-Python: >=3.8
License-File: LICENCE
Requires-Dist: requests ==2.31.0
